{
  "hero": {
    "tagline": "Trusted general_contractor",
    "title": "EC's Trusted general_contractor",
    "subtitle": "Quality Work. Fair Prices. Done Right.",
    "description": "Jeremiah has been serving EC with professional general_contractor services. Licensed, insured, and backed by our satisfaction guarantee.",
    "image": "/images/hero.jpg",
    "animation": "ken-burns",
    "primaryButtonText": "Get a Free Estimate",
    "primaryButtonLink": "#contact",
    "secondaryButtonText": "See Our Work",
    "secondaryButtonLink": "/gallery"
  },
  "trustBadges": [
    {
      "id": "licensed",
      "type": "custom",
      "label": "Licensed & Insured",
      "icon": "shield",
      "enabled": true
    },
    {
      "id": "local",
      "type": "custom",
      "label": "Locally Owned",
      "icon": "home",
      "enabled": true
    },
    {
      "id": "guaranteed",
      "type": "custom",
      "label": "Satisfaction Guaranteed",
      "icon": "check",
      "enabled": true
    },
    {
      "id": "experience",
      "type": "custom",
      "label": "Years of Experience",
      "icon": "star",
      "enabled": true
    }
  ],
  "ctaSection": {
    "title": "Ready to start your project?",
    "description": "Contact us today for a free, no-obligation estimate. We serve EC and surrounding areas.",
    "primaryButtonText": "Get a Free Estimate",
    "primaryButtonLink": "#contact",
    "secondaryButtonText": "Call 5555555555",
    "secondaryButtonLink": "tel:5555555555",
    "backgroundImage": "",
    "headline": "Ready to start your project? Get a free estimate today.",
    "subtext": "Call 5555555555 or fill out the form — we respond same day."
  },
  "serviceAreas": [
    "EC",
    "Nearby City 1",
    "Nearby City 2",
    "Nearby City 3",
    "Nearby City 4"
  ],
  "businessHours": {
    "monday": {
      "open": "7:00 AM",
      "close": "6:00 PM",
      "closed": false
    },
    "tuesday": {
      "open": "7:00 AM",
      "close": "6:00 PM",
      "closed": false
    },
    "wednesday": {
      "open": "7:00 AM",
      "close": "6:00 PM",
      "closed": false
    },
    "thursday": {
      "open": "7:00 AM",
      "close": "6:00 PM",
      "closed": false
    },
    "friday": {
      "open": "7:00 AM",
      "close": "6:00 PM",
      "closed": false
    },
    "saturday": {
      "open": "8:00 AM",
      "close": "4:00 PM",
      "closed": false
    },
    "sunday": {
      "open": "Closed",
      "close": "Closed",
      "closed": true
    }
  },
  "aboutSection": {
    "title": "Why Homeowners Choose Jeremiah",
    "text": "Jeremiah deliver quality workmanship to homeowners throughout EC.",
    "image": ""
  }
}